pykillerx/__init__.py
pykillerx/blacklist/__init__.py
pykillerx/blacklist/support.py
pykillerx/button/__init__.py
pykillerx/button/button.py
pykillerx/extra/__init__.py
pykillerx/extra/hosted.py
pykillerx/help/__init__.py
pykillerx/help/help.py
pykillerx/helper/__init__.py
pykillerx/helper/basic.py
pykillerx/helper/call.py
pykillerx/helper/check_size.py
pykillerx/helper/clear_string.py
pykillerx/helper/content.py
pykillerx/helper/data.py
pykillerx/helper/dl_helpers.py
pykillerx/helper/goblok.py
pykillerx/helper/hacking.py
pykillerx/helper/inline.py
pykillerx/helper/interval.py
pykillerx/helper/parser.py
pykillerx/helper/rendy.py
pykillerx/helper/repo.py
pykillerx/helper/sticker.py
pykillerx/helper/tools.py
pykillerx/helper/utility.py
pykillerx/helper/what.py
pykillerx/methods/__init__.py
pykillerx/methods/queue.py
pykillerx/openai/__init__.py
pykillerx/openai/create.py
pykillerx/py_trans/__init__.py
pykillerx/py_trans/async_translator.py
pykillerx/py_trans/errors.py
pykillerx/py_trans/language_codes.py
pykillerx/py_trans/translator.py
pykillerx/pyrogram/__init__.py
pykillerx/pyrogram/_wrappers.py
pykillerx/pyrogram/func.py
pykillerx/pyrogram/misc.py
pykillerx/pyrogram/sections.py
pykillerx/pyrogram/toolbot.py
pykillerx/pyrogram/tools.py
pykillerx/types/__init__.py
pykillerx/types/mod.py
pykillerx-0.1.27.dist-info/LICENSE
pykillerx-0.1.27.dist-info/METADATA
pykillerx-0.1.27.dist-info/WHEEL
pykillerx-0.1.27.dist-info/top_level.txt
pykillerx-0.1.27.dist-info/RECORD
