Metadata-Version: 2.1
Name: pykillerx
Version: 0.1.27
Summary: DarkWeb Userbot Pyrogram
Home-page: https://github.com/TeamkillerX
Author: TeamKillerX
Author-email: killerx@randydev.my.id
License: MIT
Classifier: License :: OSI Approved :: MIT License
Classifier: Programming Language :: Python
Classifier: Programming Language :: Python :: 3
Classifier: Programming Language :: Python :: 3.6
Classifier: Programming Language :: Python :: 3.7
Classifier: Programming Language :: Python :: 3.8
Classifier: Programming Language :: Python :: Implementation :: CPython
Classifier: Programming Language :: Python :: Implementation :: PyPy
Requires-Python: ~=3.8,~=3.9
License-File: LICENSE
Requires-Dist: pyrogram
Requires-Dist: aiohttp
Requires-Dist: requests
Requires-Dist: python-dotenv
Requires-Dist: pytgcalls (==3.0.0.dev24)
Requires-Dist: numpy
